setup.py
ET0_EraInterim.egg-info/PKG-INFO
ET0_EraInterim.egg-info/SOURCES.txt
ET0_EraInterim.egg-info/dependency_links.txt
ET0_EraInterim.egg-info/requires.txt
ET0_EraInterim.egg-info/top_level.txt
python/calculateETfromERAI.py
python/utils.py