Metadata-Version: 1.1
Name: ET0-EraInterim
Version: 0.0.1
Summary: A utility to produce ET0 based on ERA INTERIM data 
Home-page: https://github.com/yoannMoreau/ET0_EraInterim
Author: Yoann M
Author-email: yoann.moreau@gmail.com
License: CCO
Platform: Posix;
Classifier: Development Status :: 3 - Alpha
